README.md
yaml/__init__.py
yaml/composer.py
yaml/constructor.py
yaml/cyaml.py
yaml/dumper.py
yaml/emitter.py
yaml/error.py
yaml/events.py
yaml/loader.py
yaml/nodes.py
yaml/parser.py
yaml/reader.py
yaml/representer.py
yaml/resolver.py
yaml/scanner.py
yaml/serializer.py
yaml/tokens.py
lazyaml-6.0.4.dist-info/WHEEL
lazyaml-6.0.4.dist-info/METADATA
lazyaml-6.0.4.dist-info/LICENSE
lazyaml-6.0.4.dist-info/RECORD
